[
  {
    "direction": "Flat", 
    "noise": 1, 
    "sysTime": "2016-02-08T08:47:39.657-0800", 
    "xDrip_calculated_value": 150, 
    "xDrip_raw": 175, 
    "dateString": "2016-02-08T08:47:39.657-0800", 
    "sgv": 150, 
    "date": 1454950059657, 
    "xDrip_filtered": 178, 
    "xDrip_age_adjusted_raw_value": 175, 
    "unfiltered": 175000, 
    "rssi": 100, 
    "device": "xDrip-DexcomShare", 
    "filtered": 178000, 
    "xDrip_calculated_current_slope": -6.668244817940246e-06, 
    "_id": "56b8c6c407f60885b3446259", 
    "type": "sgv"
  }, 
  {
    "direction": "Flat", 
    "noise": 1, 
    "sysTime": "2016-02-08T08:42:39.728-0800", 
    "xDrip_calculated_value": 152, 
    "xDrip_raw": 177, 
    "dateString": "2016-02-08T08:42:39.728-0800", 
    "sgv": 152, 
    "date": 1454949759728, 
    "xDrip_filtered": 181, 
    "xDrip_age_adjusted_raw_value": 177, 
    "unfiltered": 177000, 
    "rssi": 100, 
    "device": "xDrip-DexcomShare", 
    "filtered": 181000, 
    "xDrip_calculated_current_slope": -6.668244817940246e-06, 
    "_id": "56b8c59607f60885b3446255", 
    "type": "sgv"
  }, 
  {
    "direction": "Flat", 
    "noise": 1, 
    "sysTime": "2016-02-08T08:37:39.907-0800", 
    "xDrip_calculated_value": 154, 
    "xDrip_raw": 179, 
    "dateString": "2016-02-08T08:37:39.907-0800", 
    "sgv": 154, 
    "date": 1454949459907, 
    "xDrip_filtered": 183, 
    "xDrip_age_adjusted_raw_value": 179, 
    "unfiltered": 179000, 
    "rssi": 100, 
    "device": "xDrip-DexcomShare", 
    "filtered": 183000, 
    "xDrip_calculated_current_slope": -6.668244817940246e-06, 
    "_id": "56b8c48c07f60885b344624e", 
    "type": "sgv"
  }, 
  {
    "direction": "Flat", 
    "noise": 1, 
    "sysTime": "2016-02-08T08:32:39.736-0800", 
    "xDrip_calculated_value": 156, 
    "xDrip_raw": 182, 
    "dateString": "2016-02-08T08:32:39.736-0800", 
    "sgv": 156, 
    "date": 1454949159736, 
    "xDrip_filtered": 184, 
    "xDrip_age_adjusted_raw_value": 182, 
    "unfiltered": 182000, 
    "rssi": 100, 
    "device": "xDrip-DexcomShare", 
    "filtered": 184000, 
    "xDrip_calculated_current_slope": -6.668244817940246e-06, 
    "_id": "56b8c33d07f60885b344624d", 
    "type": "sgv"
  }, 
  {
    "direction": "Flat", 
    "noise": 1, 
    "sysTime": "2016-02-08T08:27:39.684-0800", 
    "xDrip_calculated_value": 158, 
    "xDrip_raw": 183, 
    "dateString": "2016-02-08T08:27:39.684-0800", 
    "sgv": 158, 
    "date": 1454948859684, 
    "xDrip_filtered": 183, 
    "xDrip_age_adjusted_raw_value": 183, 
    "unfiltered": 183000, 
    "rssi": 100, 
    "device": "xDrip-DexcomShare", 
    "filtered": 183000, 
    "xDrip_calculated_current_slope": -6.668244817940246e-06, 
    "_id": "56b8c21307f60885b344624c", 
    "type": "sgv"
  }, 
  {
    "direction": "Flat", 
    "noise": 1, 
    "sysTime": "2016-02-08T08:22:39.816-0800", 
    "xDrip_calculated_value": 160, 
    "xDrip_raw": 186, 
    "dateString": "2016-02-08T08:22:39.816-0800", 
    "sgv": 160, 
    "date": 1454948559816, 
    "xDrip_filtered": 181, 
    "xDrip_age_adjusted_raw_value": 186, 
    "unfiltered": 186000, 
    "rssi": 100, 
    "device": "xDrip-DexcomShare", 
    "filtered": 181000, 
    "xDrip_calculated_current_slope": -6.668244817940246e-06, 
    "_id": "56b8c13707f60885b3446248", 
    "type": "sgv"
  }, 
  {
    "direction": "Flat", 
    "noise": 1, 
    "sysTime": "2016-02-08T08:17:39.768-0800", 
    "xDrip_calculated_value": 158, 
    "xDrip_raw": 183, 
    "dateString": "2016-02-08T08:17:39.768-0800", 
    "sgv": 158, 
    "date": 1454948259768, 
    "xDrip_filtered": 179, 
    "xDrip_age_adjusted_raw_value": 183, 
    "unfiltered": 183000, 
    "rssi": 100, 
    "device": "xDrip-DexcomShare", 
    "filtered": 179000, 
    "xDrip_calculated_current_slope": 6.665622385826221e-06, 
    "_id": "56b8bfcc07f60885b3446247", 
    "type": "sgv"
  }, 
  {
    "direction": "Flat", 
    "noise": 1, 
    "sysTime": "2016-02-08T08:12:39.721-0800", 
    "xDrip_calculated_value": 156, 
    "xDrip_raw": 181, 
    "dateString": "2016-02-08T08:12:39.721-0800", 
    "sgv": 156, 
    "date": 1454947959721, 
    "xDrip_filtered": 178, 
    "xDrip_age_adjusted_raw_value": 181, 
    "unfiltered": 181000, 
    "rssi": 100, 
    "device": "xDrip-DexcomShare", 
    "filtered": 178000, 
    "xDrip_calculated_current_slope": 1.667622770388356e-05, 
    "_id": "56b8be8c07f60885b3446240", 
    "type": "sgv"
  }, 
  {
    "direction": "Flat", 
    "noise": 1, 
    "sysTime": "2016-02-08T08:07:39.893-0800", 
    "xDrip_calculated_value": 151, 
    "xDrip_raw": 177, 
    "dateString": "2016-02-08T08:07:39.893-0800", 
    "sgv": 151, 
    "date": 1454947659893, 
    "xDrip_filtered": 177, 
    "xDrip_age_adjusted_raw_value": 177, 
    "unfiltered": 177000, 
    "rssi": 100, 
    "device": "xDrip-DexcomShare", 
    "filtered": 177000, 
    "xDrip_calculated_current_slope": 0, 
    "_id": "56b8bd8107f60885b344623c", 
    "type": "sgv"
  }, 
  {
    "direction": "Flat", 
    "noise": 1, 
    "sysTime": "2016-02-08T08:02:39.894-0800", 
    "xDrip_calculated_value": 151, 
    "xDrip_raw": 177, 
    "dateString": "2016-02-08T08:02:39.894-0800", 
    "sgv": 151, 
    "date": 1454947359894, 
    "xDrip_filtered": 175, 
    "xDrip_age_adjusted_raw_value": 177, 
    "unfiltered": 177000, 
    "rssi": 100, 
    "device": "xDrip-DexcomShare", 
    "filtered": 175000, 
    "xDrip_calculated_current_slope": -3.332711227237582e-06, 
    "_id": "56b8bc3607f60885b3446238", 
    "type": "sgv"
  }
]