[
  {
    "direction": "Flat", 
    "noise": 1, 
    "sysTime": "2016-02-13T18:27:17.417-0800", 
    "xDrip_calculated_value": 173, 
    "xDrip_raw": 230, 
    "dateString": "2016-02-13T18:27:17.417-0800", 
    "sgv": 173, 
    "date": 1455416837417, 
    "xDrip_filtered": 228, 
    "xDrip_age_adjusted_raw_value": 230, 
    "unfiltered": 230000, 
    "rssi": 100, 
    "device": "xDrip-DexcomShare", 
    "filtered": 228000, 
    "xDrip_calculated_current_slope": 0, 
    "_id": "56bfe63e07f60885b344746c", 
    "type": "sgv"
  }, 
  {
    "direction": "Flat", 
    "noise": 1, 
    "sysTime": "2016-02-13T18:22:16.903-0800", 
    "xDrip_calculated_value": 173, 
    "xDrip_raw": 229, 
    "dateString": "2016-02-13T18:22:16.903-0800", 
    "sgv": 173, 
    "date": 1455416536903, 
    "xDrip_filtered": 225, 
    "xDrip_age_adjusted_raw_value": 229, 
    "unfiltered": 229000, 
    "rssi": 100, 
    "device": "xDrip-DexcomShare", 
    "filtered": 225000, 
    "xDrip_calculated_current_slope": 3.337672307332866e-06, 
    "_id": "56bfe4f207f60885b3447468", 
    "type": "sgv"
  }, 
  {
    "direction": "Flat", 
    "noise": 1, 
    "sysTime": "2016-02-13T18:17:17.293-0800", 
    "xDrip_calculated_value": 172, 
    "xDrip_raw": 227, 
    "dateString": "2016-02-13T18:17:17.293-0800", 
    "sgv": 172, 
    "date": 1455416237293, 
    "xDrip_filtered": 223, 
    "xDrip_age_adjusted_raw_value": 227, 
    "unfiltered": 227000, 
    "rssi": 100, 
    "device": "xDrip-DexcomShare", 
    "filtered": 223000, 
    "xDrip_calculated_current_slope": 9.998300288950879e-06, 
    "_id": "56bfe3ef07f60885b3447467", 
    "type": "sgv"
  }, 
  {
    "direction": "Flat", 
    "noise": 1, 
    "sysTime": "2016-02-13T18:12:17.242-0800", 
    "xDrip_calculated_value": 169, 
    "xDrip_raw": 224, 
    "dateString": "2016-02-13T18:12:17.242-0800", 
    "sgv": 169, 
    "date": 1455415937242, 
    "xDrip_filtered": 221, 
    "xDrip_age_adjusted_raw_value": 224, 
    "unfiltered": 224000, 
    "rssi": 100, 
    "device": "xDrip-DexcomShare", 
    "filtered": 221000, 
    "xDrip_calculated_current_slope": 6.6666444445185185e-06, 
    "_id": "56bfe2ba07f60885b3447466", 
    "type": "sgv"
  }, 
  {
    "direction": "Flat", 
    "noise": 1, 
    "sysTime": "2016-02-13T18:07:17.241-0800", 
    "xDrip_calculated_value": 167, 
    "xDrip_raw": 221, 
    "dateString": "2016-02-13T18:07:17.241-0800", 
    "sgv": 167, 
    "date": 1455415637241, 
    "xDrip_filtered": 218, 
    "xDrip_age_adjusted_raw_value": 221, 
    "unfiltered": 221000, 
    "rssi": 100, 
    "device": "xDrip-DexcomShare", 
    "filtered": 218000, 
    "xDrip_calculated_current_slope": 6.682280929772569e-06, 
    "_id": "56bfe16c07f60885b3447465", 
    "type": "sgv"
  }, 
  {
    "direction": "Flat", 
    "noise": 1, 
    "sysTime": "2016-02-13T18:02:17.942-0800", 
    "xDrip_calculated_value": 165, 
    "xDrip_raw": 219, 
    "dateString": "2016-02-13T18:02:17.942-0800", 
    "sgv": 165, 
    "date": 1455415337942, 
    "xDrip_filtered": 216, 
    "xDrip_age_adjusted_raw_value": 219, 
    "unfiltered": 219000, 
    "rssi": 100, 
    "device": "xDrip-DexcomShare", 
    "filtered": 216000, 
    "xDrip_calculated_current_slope": 3.334233576398961e-06, 
    "_id": "56bfe04307f60885b3447464", 
    "type": "sgv"
  }, 
  {
    "direction": "Flat", 
    "noise": 1, 
    "sysTime": "2016-02-13T17:57:18.023-0800", 
    "xDrip_calculated_value": 164, 
    "xDrip_raw": 217, 
    "dateString": "2016-02-13T17:57:18.023-0800", 
    "sgv": 164, 
    "date": 1455415038023, 
    "xDrip_filtered": 212, 
    "xDrip_age_adjusted_raw_value": 217, 
    "unfiltered": 217000, 
    "rssi": 100, 
    "device": "xDrip-DexcomShare", 
    "filtered": 212000, 
    "xDrip_calculated_current_slope": 9.997933760356193e-06, 
    "_id": "56bfdf3507f60885b3447463", 
    "type": "sgv"
  }, 
  {
    "direction": "Flat", 
    "noise": 1, 
    "sysTime": "2016-02-13T17:52:17.961-0800", 
    "xDrip_calculated_value": 161, 
    "xDrip_raw": 214, 
    "dateString": "2016-02-13T17:52:17.961-0800", 
    "sgv": 161, 
    "date": 1455414737961, 
    "xDrip_filtered": 208, 
    "xDrip_age_adjusted_raw_value": 214, 
    "unfiltered": 214000, 
    "rssi": 100, 
    "device": "xDrip-DexcomShare", 
    "filtered": 208000, 
    "xDrip_calculated_current_slope": 9.998433578739331e-06, 
    "_id": "56bfddef07f60885b3447462", 
    "type": "sgv"
  }, 
  {
    "direction": "FortyFiveUp", 
    "noise": 1, 
    "sysTime": "2016-02-13T17:47:17.914-0800", 
    "xDrip_calculated_value": 158, 
    "xDrip_raw": 210, 
    "dateString": "2016-02-13T17:47:17.914-0800", 
    "sgv": 158, 
    "date": 1455414437914, 
    "xDrip_filtered": 202, 
    "xDrip_age_adjusted_raw_value": 210, 
    "unfiltered": 210000, 
    "rssi": 100, 
    "device": "xDrip-DexcomShare", 
    "filtered": 202000, 
    "xDrip_calculated_current_slope": 1.3320235102149553e-05, 
    "_id": "56bfdcc407f60885b3447461", 
    "type": "sgv"
  }, 
  {
    "direction": "FortyFiveUp", 
    "noise": 1, 
    "sysTime": "2016-02-13T17:42:17.619-0800", 
    "xDrip_calculated_value": 154, 
    "xDrip_raw": 205, 
    "dateString": "2016-02-13T17:42:17.619-0800", 
    "sgv": 154, 
    "date": 1455414137619, 
    "xDrip_filtered": 194, 
    "xDrip_age_adjusted_raw_value": 205, 
    "unfiltered": 205000, 
    "rssi": 100, 
    "device": "xDrip-DexcomShare", 
    "filtered": 194000, 
    "xDrip_calculated_current_slope": 1.999966667222213e-05, 
    "_id": "56bfdbb207f60885b3447460", 
    "type": "sgv"
  }
]