[
  {
    "direction": "Flat", 
    "noise": 1, 
    "sysTime": "2016-02-13T06:47:18.965-0800", 
    "xDrip_calculated_value": 108, 
    "xDrip_raw": 136, 
    "dateString": "2016-02-13T06:47:18.965-0800", 
    "sgv": 108, 
    "date": 1455374838965, 
    "xDrip_filtered": 134, 
    "xDrip_age_adjusted_raw_value": 136, 
    "unfiltered": 136000, 
    "rssi": 100, 
    "device": "xDrip-DexcomShare", 
    "filtered": 134000, 
    "xDrip_calculated_current_slope": 3.325551542723361e-06, 
    "_id": "56bf424e07f60885b34472cf", 
    "type": "sgv"
  }, 
  {
    "direction": "Flat", 
    "noise": 1, 
    "sysTime": "2016-02-13T06:42:18.263-0800", 
    "xDrip_calculated_value": 107, 
    "xDrip_raw": 135, 
    "dateString": "2016-02-13T06:42:18.263-0800", 
    "sgv": 107, 
    "date": 1455374538263, 
    "xDrip_filtered": 132, 
    "xDrip_age_adjusted_raw_value": 135, 
    "unfiltered": 135000, 
    "rssi": 100, 
    "device": "xDrip-DexcomShare", 
    "filtered": 132000, 
    "xDrip_calculated_current_slope": 3.343162230290387e-06, 
    "_id": "56bf40e507f60885b34472c8", 
    "type": "sgv"
  }, 
  {
    "direction": "Flat", 
    "noise": 1, 
    "sysTime": "2016-02-13T06:37:19.145-0800", 
    "xDrip_calculated_value": 106, 
    "xDrip_raw": 133, 
    "dateString": "2016-02-13T06:37:19.145-0800", 
    "sgv": 106, 
    "date": 1455374239145, 
    "xDrip_filtered": 131, 
    "xDrip_age_adjusted_raw_value": 133, 
    "unfiltered": 133000, 
    "rssi": 100, 
    "device": "xDrip-DexcomShare", 
    "filtered": 131000, 
    "xDrip_calculated_current_slope": 6.653249280617422e-06, 
    "_id": "56bf3fdd07f60885b34472c4", 
    "type": "sgv"
  }, 
  {
    "direction": "Flat", 
    "noise": 1, 
    "sysTime": "2016-02-13T06:32:18.540-0800", 
    "xDrip_calculated_value": 104, 
    "xDrip_raw": 132, 
    "dateString": "2016-02-13T06:32:18.540-0800", 
    "sgv": 104, 
    "date": 1455373938540, 
    "xDrip_filtered": 129, 
    "xDrip_age_adjusted_raw_value": 132, 
    "unfiltered": 132000, 
    "rssi": 100, 
    "device": "xDrip-DexcomShare", 
    "filtered": 129000, 
    "xDrip_calculated_current_slope": 1.0019002708470399e-05, 
    "_id": "56bf3e8e07f60885b34472c2", 
    "type": "sgv"
  }, 
  {
    "direction": "Flat", 
    "noise": 1, 
    "sysTime": "2016-02-13T06:27:19.109-0800", 
    "xDrip_calculated_value": 101, 
    "xDrip_raw": 129, 
    "dateString": "2016-02-13T06:27:19.109-0800", 
    "sgv": 101, 
    "date": 1455373639109, 
    "xDrip_filtered": 127, 
    "xDrip_age_adjusted_raw_value": 129, 
    "unfiltered": 129000, 
    "rssi": 100, 
    "device": "xDrip-DexcomShare", 
    "filtered": 127000, 
    "xDrip_calculated_current_slope": 0, 
    "_id": "56bf3d8407f60885b34472c1", 
    "type": "sgv"
  }, 
  {
    "direction": "Flat", 
    "noise": 1, 
    "sysTime": "2016-02-13T06:22:18.402-0800", 
    "xDrip_calculated_value": 101, 
    "xDrip_raw": 128, 
    "dateString": "2016-02-13T06:22:18.402-0800", 
    "sgv": 101, 
    "date": 1455373338402, 
    "xDrip_filtered": 124, 
    "xDrip_age_adjusted_raw_value": 128, 
    "unfiltered": 128000, 
    "rssi": 100, 
    "device": "xDrip-DexcomShare", 
    "filtered": 124000, 
    "xDrip_calculated_current_slope": 3.3365252758472274e-06, 
    "_id": "56bf3c3407f60885b34472ba", 
    "type": "sgv"
  }, 
  {
    "direction": "Flat", 
    "noise": 1, 
    "sysTime": "2016-02-13T06:17:18.689-0800", 
    "xDrip_calculated_value": 100, 
    "xDrip_raw": 127, 
    "dateString": "2016-02-13T06:17:18.689-0800", 
    "sgv": 100, 
    "date": 1455373038689, 
    "xDrip_filtered": 121, 
    "xDrip_age_adjusted_raw_value": 127, 
    "unfiltered": 127000, 
    "rssi": 100, 
    "device": "xDrip-DexcomShare", 
    "filtered": 121000, 
    "xDrip_calculated_current_slope": 1.669950903443439e-05, 
    "_id": "56bf3b0807f60885b34472b6", 
    "type": "sgv"
  }, 
  {
    "direction": "Flat", 
    "noise": 1, 
    "sysTime": "2016-02-13T06:12:19.279-0800", 
    "xDrip_calculated_value": 95, 
    "xDrip_raw": 122, 
    "dateString": "2016-02-13T06:12:19.279-0800", 
    "sgv": 95, 
    "date": 1455372739279, 
    "xDrip_filtered": 119, 
    "xDrip_age_adjusted_raw_value": 122, 
    "unfiltered": 122000, 
    "rssi": 100, 
    "device": "xDrip-DexcomShare", 
    "filtered": 119000, 
    "xDrip_calculated_current_slope": 6.668222585269896e-06, 
    "_id": "56bf3a0007f60885b34472b5", 
    "type": "sgv"
  }, 
  {
    "direction": "Flat", 
    "noise": 1, 
    "sysTime": "2016-02-13T06:07:19.349-0800", 
    "xDrip_calculated_value": 93, 
    "xDrip_raw": 120, 
    "dateString": "2016-02-13T06:07:19.349-0800", 
    "sgv": 93, 
    "date": 1455372439349, 
    "xDrip_filtered": 118, 
    "xDrip_age_adjusted_raw_value": 120, 
    "unfiltered": 120000, 
    "rssi": 100, 
    "device": "xDrip-DexcomShare", 
    "filtered": 118000, 
    "xDrip_calculated_current_slope": 6.6665555574073766e-06, 
    "_id": "56bf38b007f60885b34472b1", 
    "type": "sgv"
  }, 
  {
    "direction": "Flat", 
    "noise": 1, 
    "sysTime": "2016-02-13T06:02:19.344-0800", 
    "xDrip_calculated_value": 91, 
    "xDrip_raw": 118, 
    "dateString": "2016-02-13T06:02:19.344-0800", 
    "sgv": 91, 
    "date": 1455372139344, 
    "xDrip_filtered": 118, 
    "xDrip_age_adjusted_raw_value": 118, 
    "unfiltered": 118000, 
    "rssi": 100, 
    "device": "xDrip-DexcomShare", 
    "filtered": 118000, 
    "xDrip_calculated_current_slope": 3.3328223005805777e-06, 
    "_id": "56bf378407f60885b34472b0", 
    "type": "sgv"
  }
]