[
  {
    "direction": "Flat", 
    "noise": 1, 
    "sysTime": "2016-02-09T06:07:35.225-0800", 
    "xDrip_calculated_value": 113, 
    "xDrip_raw": 143, 
    "dateString": "2016-02-09T06:07:35.225-0800", 
    "sgv": 113, 
    "date": 1455026855225, 
    "xDrip_filtered": 145, 
    "xDrip_age_adjusted_raw_value": 143, 
    "unfiltered": 143000, 
    "rssi": 100, 
    "device": "xDrip-DexcomShare", 
    "filtered": 145000, 
    "xDrip_calculated_current_slope": -3.334066828035501e-06, 
    "_id": "56b9f2c007f60885b3446560", 
    "type": "sgv"
  }, 
  {
    "direction": "Flat", 
    "noise": 1, 
    "sysTime": "2016-02-09T06:02:35.291-0800", 
    "xDrip_calculated_value": 114, 
    "xDrip_raw": 144, 
    "dateString": "2016-02-09T06:02:35.291-0800", 
    "sgv": 114, 
    "date": 1455026555291, 
    "xDrip_filtered": 147, 
    "xDrip_age_adjusted_raw_value": 144, 
    "unfiltered": 144000, 
    "rssi": 100, 
    "device": "xDrip-DexcomShare", 
    "filtered": 147000, 
    "xDrip_calculated_current_slope": -3.3327778703549408e-06, 
    "_id": "56b9f1b307f60885b344655f", 
    "type": "sgv"
  }, 
  {
    "direction": "Flat", 
    "noise": 1, 
    "sysTime": "2016-02-09T05:57:35.241-0800", 
    "xDrip_calculated_value": 115, 
    "xDrip_raw": 145, 
    "dateString": "2016-02-09T05:57:35.241-0800", 
    "sgv": 115, 
    "date": 1455026255241, 
    "xDrip_filtered": 148, 
    "xDrip_age_adjusted_raw_value": 145, 
    "unfiltered": 145000, 
    "rssi": 100, 
    "device": "xDrip-DexcomShare", 
    "filtered": 148000, 
    "xDrip_calculated_current_slope": -6.682236277192525e-06, 
    "_id": "56b9f06607f60885b344655b", 
    "type": "sgv"
  }, 
  {
    "direction": "Flat", 
    "noise": 1, 
    "sysTime": "2016-02-09T05:52:35.940-0800", 
    "xDrip_calculated_value": 117, 
    "xDrip_raw": 147, 
    "dateString": "2016-02-09T05:52:35.940-0800", 
    "sgv": 117, 
    "date": 1455025955940, 
    "xDrip_filtered": 148, 
    "xDrip_age_adjusted_raw_value": 147, 
    "unfiltered": 147000, 
    "rssi": 100, 
    "device": "xDrip-DexcomShare", 
    "filtered": 148000, 
    "xDrip_calculated_current_slope": -3.3341335253794245e-06, 
    "_id": "56b9ef3907f60885b3446557", 
    "type": "sgv"
  }, 
  {
    "direction": "Flat", 
    "noise": 1, 
    "sysTime": "2016-02-09T05:47:36.012-0800", 
    "xDrip_calculated_value": 118, 
    "xDrip_raw": 148, 
    "dateString": "2016-02-09T05:47:36.012-0800", 
    "sgv": 118, 
    "date": 1455025656012, 
    "xDrip_filtered": 147, 
    "xDrip_age_adjusted_raw_value": 148, 
    "unfiltered": 148000, 
    "rssi": 100, 
    "device": "xDrip-DexcomShare", 
    "filtered": 147000, 
    "xDrip_calculated_current_slope": 0, 
    "_id": "56b9ee2e07f60885b3446556", 
    "type": "sgv"
  }, 
  {
    "direction": "Flat", 
    "noise": 1, 
    "sysTime": "2016-02-09T05:42:35.965-0800", 
    "xDrip_calculated_value": 118, 
    "xDrip_raw": 148, 
    "dateString": "2016-02-09T05:42:35.965-0800", 
    "sgv": 118, 
    "date": 1455025355965, 
    "xDrip_filtered": 144, 
    "xDrip_age_adjusted_raw_value": 148, 
    "unfiltered": 148000, 
    "rssi": 100, 
    "device": "xDrip-DexcomShare", 
    "filtered": 144000, 
    "xDrip_calculated_current_slope": 9.99990000099999e-06, 
    "_id": "56b9ece207f60885b3446555", 
    "type": "sgv"
  }, 
  {
    "direction": "Flat", 
    "noise": 1, 
    "sysTime": "2016-02-09T05:37:35.962-0800", 
    "xDrip_calculated_value": 115, 
    "xDrip_raw": 145, 
    "dateString": "2016-02-09T05:37:35.962-0800", 
    "sgv": 115, 
    "date": 1455025055962, 
    "xDrip_filtered": 140, 
    "xDrip_age_adjusted_raw_value": 145, 
    "unfiltered": 145000, 
    "rssi": 100, 
    "device": "xDrip-DexcomShare", 
    "filtered": 140000, 
    "xDrip_calculated_current_slope": 9.990209594597294e-06, 
    "_id": "56b9ebb507f60885b3446554", 
    "type": "sgv"
  }, 
  {
    "direction": "Flat", 
    "noise": 1, 
    "sysTime": "2016-02-09T05:32:35.668-0800", 
    "xDrip_calculated_value": 112, 
    "xDrip_raw": 142, 
    "dateString": "2016-02-09T05:32:35.668-0800", 
    "sgv": 112, 
    "date": 1455024755668, 
    "xDrip_filtered": 136, 
    "xDrip_age_adjusted_raw_value": 142, 
    "unfiltered": 142000, 
    "rssi": 100, 
    "device": "xDrip-DexcomShare", 
    "filtered": 136000, 
    "xDrip_calculated_current_slope": 9.998533548412899e-06, 
    "_id": "56b9eac807f60885b3446553", 
    "type": "sgv"
  }, 
  {
    "direction": "Flat", 
    "noise": 1, 
    "sysTime": "2016-02-09T05:27:35.624-0800", 
    "xDrip_calculated_value": 109, 
    "xDrip_raw": 139, 
    "dateString": "2016-02-09T05:27:35.624-0800", 
    "sgv": 109, 
    "date": 1455024455624, 
    "xDrip_filtered": 131, 
    "xDrip_age_adjusted_raw_value": 139, 
    "unfiltered": 139000, 
    "rssi": 100, 
    "device": "xDrip-DexcomShare", 
    "filtered": 131000, 
    "xDrip_calculated_current_slope": 1.333115591120117e-05, 
    "_id": "56b9e95d07f60885b344654f", 
    "type": "sgv"
  }, 
  {
    "direction": "Flat", 
    "noise": 1, 
    "sysTime": "2016-02-09T05:22:35.575-0800", 
    "xDrip_calculated_value": 105, 
    "xDrip_raw": 135, 
    "dateString": "2016-02-09T05:22:35.575-0800", 
    "sgv": 105, 
    "date": 1455024155575, 
    "xDrip_filtered": 128, 
    "xDrip_age_adjusted_raw_value": 135, 
    "unfiltered": 135000, 
    "rssi": 100, 
    "device": "xDrip-DexcomShare", 
    "filtered": 128000, 
    "xDrip_calculated_current_slope": 1.6670278560354743e-05, 
    "_id": "56b9e83107f60885b344654b", 
    "type": "sgv"
  }
]