[
  {
    "direction": "FortyFiveUp", 
    "noise": 1, 
    "sysTime": "2016-02-06T07:42:46.119-0800", 
    "xDrip_calculated_value": 105, 
    "xDrip_raw": 98, 
    "dateString": "2016-02-06T07:42:46.119-0800", 
    "sgv": 105, 
    "date": 1454773366119, 
    "xDrip_filtered": 82, 
    "xDrip_age_adjusted_raw_value": 98, 
    "unfiltered": 98000, 
    "rssi": 100, 
    "device": "xDrip-DexcomShare", 
    "filtered": 82000, 
    "xDrip_calculated_current_slope": 3.994833348868796e-05, 
    "_id": "56b6148e07f60885b3445c6e", 
    "type": "sgv"
  }, 
  {
    "direction": "FortyFiveUp", 
    "noise": 1, 
    "sysTime": "2016-02-06T07:37:45.731-0800", 
    "xDrip_calculated_value": 93, 
    "xDrip_raw": 88, 
    "dateString": "2016-02-06T07:37:45.731-0800", 
    "sgv": 93, 
    "date": 1454773065731, 
    "xDrip_filtered": 74, 
    "xDrip_age_adjusted_raw_value": 88, 
    "unfiltered": 88000, 
    "rssi": 100, 
    "device": "xDrip-DexcomShare", 
    "filtered": 74000, 
    "xDrip_calculated_current_slope": 3.6666666666666666e-05, 
    "_id": "56b6138107f60885b3445c6d", 
    "type": "sgv"
  }, 
  {
    "direction": "Flat", 
    "noise": 1, 
    "sysTime": "2016-02-06T07:32:45.731-0800", 
    "xDrip_calculated_value": 82, 
    "xDrip_raw": 79, 
    "dateString": "2016-02-06T07:32:45.731-0800", 
    "sgv": 82, 
    "date": 1454772765731, 
    "xDrip_filtered": 70, 
    "xDrip_age_adjusted_raw_value": 79, 
    "unfiltered": 79000, 
    "rssi": 100, 
    "device": "xDrip-DexcomShare", 
    "filtered": 70000, 
    "xDrip_calculated_current_slope": 3.0040354209154297e-05, 
    "_id": "56b6123c07f60885b3445c66", 
    "type": "sgv"
  }, 
  {
    "direction": "Flat", 
    "noise": 1, 
    "sysTime": "2016-02-06T07:27:46.134-0800", 
    "xDrip_calculated_value": 73, 
    "xDrip_raw": 72, 
    "dateString": "2016-02-06T07:27:46.134-0800", 
    "sgv": 73, 
    "date": 1454772466134, 
    "xDrip_filtered": 71, 
    "xDrip_age_adjusted_raw_value": 72, 
    "unfiltered": 72000, 
    "rssi": 100, 
    "device": "xDrip-DexcomShare", 
    "filtered": 71000, 
    "xDrip_calculated_current_slope": 1.0016360054756101e-05, 
    "_id": "56b6110f07f60885b3445c65", 
    "type": "sgv"
  }, 
  {
    "direction": "FortyFiveDown", 
    "noise": 1, 
    "sysTime": "2016-02-06T07:22:46.624-0800", 
    "xDrip_calculated_value": 70, 
    "xDrip_raw": 70, 
    "dateString": "2016-02-06T07:22:46.624-0800", 
    "sgv": 70, 
    "date": 1454772166624, 
    "xDrip_filtered": 79, 
    "xDrip_age_adjusted_raw_value": 70, 
    "unfiltered": 70000, 
    "rssi": 100, 
    "device": "xDrip-DexcomShare", 
    "filtered": 79000, 
    "xDrip_calculated_current_slope": -1.3369296741568152e-05, 
    "_id": "56b6106e07f60885b3445c61", 
    "type": "sgv"
  }, 
  {
    "direction": "SingleDown", 
    "noise": 1, 
    "sysTime": "2016-02-06T07:17:47.431-0800", 
    "xDrip_calculated_value": 74, 
    "xDrip_raw": 73, 
    "dateString": "2016-02-06T07:17:47.431-0800", 
    "sgv": 74, 
    "date": 1454771867431, 
    "xDrip_filtered": 89, 
    "xDrip_age_adjusted_raw_value": 73, 
    "unfiltered": 73000, 
    "rssi": 100, 
    "device": "xDrip-DexcomShare", 
    "filtered": 89000, 
    "xDrip_calculated_current_slope": -3.6661289677513964e-05, 
    "_id": "56b60ec107f60885b3445c5d", 
    "type": "sgv"
  }, 
  {
    "direction": "SingleDown", 
    "noise": 1, 
    "sysTime": "2016-02-06T07:12:47.387-0800", 
    "xDrip_calculated_value": 85, 
    "xDrip_raw": 82, 
    "dateString": "2016-02-06T07:12:47.387-0800", 
    "sgv": 85, 
    "date": 1454771567387, 
    "xDrip_filtered": 100, 
    "xDrip_age_adjusted_raw_value": 82, 
    "unfiltered": 82000, 
    "rssi": 100, 
    "device": "xDrip-DexcomShare", 
    "filtered": 100000, 
    "xDrip_calculated_current_slope": -3.9994534080342353e-05, 
    "_id": "56b60d9d07f60885b3445c56", 
    "type": "sgv"
  }, 
  {
    "direction": "SingleDown", 
    "noise": 1, 
    "sysTime": "2016-02-06T07:07:47.346-0800", 
    "xDrip_calculated_value": 97, 
    "xDrip_raw": 92, 
    "dateString": "2016-02-06T07:07:47.346-0800", 
    "sgv": 97, 
    "date": 1454771267346, 
    "xDrip_filtered": 108, 
    "xDrip_age_adjusted_raw_value": 92, 
    "unfiltered": 92000, 
    "rssi": 100, 
    "device": "xDrip-DexcomShare", 
    "filtered": 108000, 
    "xDrip_calculated_current_slope": -5.334133453351336e-05, 
    "_id": "56b60c7c07f60885b3445c52", 
    "type": "sgv"
  }, 
  {
    "direction": "FortyFiveDown", 
    "noise": 1, 
    "sysTime": "2016-02-06T07:02:47.391-0800", 
    "xDrip_calculated_value": 113, 
    "xDrip_raw": 104, 
    "dateString": "2016-02-06T07:02:47.391-0800", 
    "sgv": 113, 
    "date": 1454770967391, 
    "xDrip_filtered": 114, 
    "xDrip_age_adjusted_raw_value": 104, 
    "unfiltered": 104000, 
    "rssi": 100, 
    "device": "xDrip-DexcomShare", 
    "filtered": 114000, 
    "xDrip_calculated_current_slope": -4.669328183731393e-05, 
    "_id": "56b60b4007f60885b3445c4b", 
    "type": "sgv"
  }, 
  {
    "direction": "FortyFiveDown", 
    "noise": 1, 
    "sysTime": "2016-02-06T06:57:47.562-0800", 
    "xDrip_calculated_value": 127, 
    "xDrip_raw": 115, 
    "dateString": "2016-02-06T06:57:47.562-0800", 
    "sgv": 127, 
    "date": 1454770667562, 
    "xDrip_filtered": 118, 
    "xDrip_age_adjusted_raw_value": 115, 
    "unfiltered": 115000, 
    "rssi": 100, 
    "device": "xDrip-DexcomShare", 
    "filtered": 118000, 
    "xDrip_calculated_current_slope": -4.669328183731393e-05, 
    "_id": "56b60b4007f60885b3445c4d", 
    "type": "sgv"
  }
]