[
  {
    "direction": "Flat", 
    "noise": 1, 
    "sysTime": "2016-02-06T17:17:43.934-0800", 
    "xDrip_calculated_value": 126, 
    "xDrip_raw": 124, 
    "dateString": "2016-02-06T17:17:43.934-0800", 
    "sgv": 126, 
    "date": 1454807863934, 
    "xDrip_filtered": 122, 
    "xDrip_age_adjusted_raw_value": 124, 
    "unfiltered": 124000, 
    "rssi": 100, 
    "device": "xDrip-DexcomShare", 
    "filtered": 122000, 
    "xDrip_calculated_current_slope": 1.0047188294355824e-05, 
    "_id": "56b69b5b07f60885b3445d67", 
    "type": "sgv"
  }, 
  {
    "direction": "Flat", 
    "noise": 1, 
    "sysTime": "2016-02-06T17:12:45.343-0800", 
    "xDrip_calculated_value": 123, 
    "xDrip_raw": 122, 
    "dateString": "2016-02-06T17:12:45.343-0800", 
    "sgv": 123, 
    "date": 1454807565343, 
    "xDrip_filtered": 121, 
    "xDrip_age_adjusted_raw_value": 122, 
    "unfiltered": 122000, 
    "rssi": 100, 
    "device": "xDrip-DexcomShare", 
    "filtered": 121000, 
    "xDrip_calculated_current_slope": 9.974001103789455e-06, 
    "_id": "56b69a4b07f60885b3445d66", 
    "type": "sgv"
  }, 
  {
    "direction": "Flat", 
    "noise": 1, 
    "sysTime": "2016-02-06T17:07:44.561-0800", 
    "xDrip_calculated_value": 120, 
    "xDrip_raw": 120, 
    "dateString": "2016-02-06T17:07:44.561-0800", 
    "sgv": 120, 
    "date": 1454807264561, 
    "xDrip_filtered": 118, 
    "xDrip_age_adjusted_raw_value": 120, 
    "unfiltered": 120000, 
    "rssi": 100, 
    "device": "xDrip-DexcomShare", 
    "filtered": 118000, 
    "xDrip_calculated_current_slope": 0, 
    "_id": "56b698f907f60885b3445d59", 
    "type": "sgv"
  }, 
  {
    "direction": "FortyFiveUp", 
    "noise": 1, 
    "sysTime": "2016-02-06T17:02:44.854-0800", 
    "xDrip_calculated_value": 120, 
    "xDrip_raw": 119, 
    "dateString": "2016-02-06T17:02:44.854-0800", 
    "sgv": 120, 
    "date": 1454806964854, 
    "xDrip_filtered": 114, 
    "xDrip_age_adjusted_raw_value": 119, 
    "unfiltered": 119000, 
    "rssi": 100, 
    "device": "xDrip-DexcomShare", 
    "filtered": 114000, 
    "xDrip_calculated_current_slope": 0, 
    "_id": "56b697cd07f60885b3445d56", 
    "type": "sgv"
  }, 
  {
    "direction": "FortyFiveUp", 
    "noise": 1, 
    "sysTime": "2016-02-06T16:57:45.355-0800", 
    "xDrip_calculated_value": 120, 
    "xDrip_raw": 119, 
    "dateString": "2016-02-06T16:57:45.355-0800", 
    "sgv": 120, 
    "date": 1454806665355, 
    "xDrip_filtered": 109, 
    "xDrip_age_adjusted_raw_value": 119, 
    "unfiltered": 119000, 
    "rssi": 100, 
    "device": "xDrip-DexcomShare", 
    "filtered": 109000, 
    "xDrip_calculated_current_slope": 3.6550436279298496e-05, 
    "_id": "56b696c207f60885b3445d54", 
    "type": "sgv"
  }, 
  {
    "direction": "Flat", 
    "noise": 1, 
    "sysTime": "2016-02-06T16:52:44.401-0800", 
    "xDrip_calculated_value": 109, 
    "xDrip_raw": 111, 
    "dateString": "2016-02-06T16:52:44.401-0800", 
    "sgv": 109, 
    "date": 1454806364401, 
    "xDrip_filtered": 106, 
    "xDrip_age_adjusted_raw_value": 111, 
    "unfiltered": 111000, 
    "rssi": 100, 
    "device": "xDrip-DexcomShare", 
    "filtered": 106000, 
    "xDrip_calculated_current_slope": 2.0041351989605218e-05, 
    "_id": "56b6957607f60885b3445d4c", 
    "type": "sgv"
  }, 
  {
    "direction": "Flat", 
    "noise": 1, 
    "sysTime": "2016-02-06T16:47:45.020-0800", 
    "xDrip_calculated_value": 103, 
    "xDrip_raw": 107, 
    "dateString": "2016-02-06T16:47:45.020-0800", 
    "sgv": 103, 
    "date": 1454806065020, 
    "xDrip_filtered": 105, 
    "xDrip_age_adjusted_raw_value": 107, 
    "unfiltered": 107000, 
    "rssi": 100, 
    "device": "xDrip-DexcomShare", 
    "filtered": 105000, 
    "xDrip_calculated_current_slope": 3.3266799733865604e-06, 
    "_id": "56b6944a07f60885b3445d4b", 
    "type": "sgv"
  }, 
  {
    "direction": "Flat", 
    "noise": 1, 
    "sysTime": "2016-02-06T16:42:44.420-0800", 
    "xDrip_calculated_value": 102, 
    "xDrip_raw": 106, 
    "dateString": "2016-02-06T16:42:44.420-0800", 
    "sgv": 102, 
    "date": 1454805764420, 
    "xDrip_filtered": 105, 
    "xDrip_age_adjusted_raw_value": 106, 
    "unfiltered": 106000, 
    "rssi": 100, 
    "device": "xDrip-DexcomShare", 
    "filtered": 105000, 
    "xDrip_calculated_current_slope": 6.665844545839347e-06, 
    "_id": "56b6932d07f60885b3445d45", 
    "type": "sgv"
  }, 
  {
    "direction": "Flat", 
    "noise": 1, 
    "sysTime": "2016-02-06T16:37:44.383-0800", 
    "xDrip_calculated_value": 100, 
    "xDrip_raw": 105, 
    "dateString": "2016-02-06T16:37:44.383-0800", 
    "sgv": 100, 
    "date": 1454805464383, 
    "xDrip_filtered": 105, 
    "xDrip_age_adjusted_raw_value": 105, 
    "unfiltered": 105000, 
    "rssi": 100, 
    "device": "xDrip-DexcomShare", 
    "filtered": 105000, 
    "xDrip_calculated_current_slope": 0, 
    "_id": "56b692f907f60885b3445d44", 
    "type": "sgv"
  }, 
  {
    "direction": "Flat", 
    "noise": 1, 
    "sysTime": "2016-02-06T16:32:44.873-0800", 
    "xDrip_calculated_value": 100, 
    "xDrip_raw": 105, 
    "dateString": "2016-02-06T16:32:44.873-0800", 
    "sgv": 100, 
    "date": 1454805164873, 
    "xDrip_filtered": 107, 
    "xDrip_age_adjusted_raw_value": 105, 
    "unfiltered": 105000, 
    "rssi": 100, 
    "device": "xDrip-DexcomShare", 
    "filtered": 107000, 
    "xDrip_calculated_current_slope": -1.001295008210619e-05, 
    "_id": "56b690c307f60885b3445d42", 
    "type": "sgv"
  }
]