{
  "device": "openaps://indy-e1", 
  "pump": {
    "battery": {
      "status": "normal", 
      "voltage": 1.54
    }, 
    "status": {
      "status": "normal", 
      "timestamp": "2016-02-10T12:06:40.000Z", 
      "bolusing": false, 
      "suspended": false
    }, 
    "reservoir": 129.6, 
    "clock": "2016-02-10T04:06:10-08:00"
  }, 
  "openaps": {
    "suggested": {
      "bg": 86, 
      "temp": "absolute", 
      "snoozeBG": 107, 
      "timestamp": "2016-02-10T12:08:09.000Z", 
      "reason": "Eventual BG 107<110, temp 0 ~< req 0.05U/hr", 
      "eventualBG": 107, 
      "mealAssist": "Off: Carbs: 0 Boluses: 0 Target: 115 Deviation: -11 BGI: 1.24", 
      "tick": -2
    }, 
    "iob": {
      "netbasalinsulin": -0.65, 
      "timestamp": "2016-02-10T12:08:08.000Z", 
      "basaliob": -0.406, 
      "activity": -0.0031, 
      "bolussnooze": 0, 
      "iob": -0.406
    }, 
    "enacted": {
      "requested": {
        "duration": 30, 
        "rate": 0, 
        "temp": "absolute"
      }, 
      "bg": 88, 
      "temp": "absolute", 
      "snoozeBG": 101, 
      "timestamp": "2016-02-10T11:53:45.000Z", 
      "reason": "Eventual BG 101<110, setting -0.25U/hr", 
      "rate": 0, 
      "eventualBG": 101, 
      "recieved": true, 
      "duration": 30, 
      "mealAssist": "Off: Carbs: 0 Boluses: 0 Target: 115 Deviation: -15 BGI: 1.12", 
      "tick": -1
    }
  }, 
  "mmtune": {
    "scanDetails": [
      [
        "916.560", 
        5, 
        -82
      ], 
      [
        "916.580", 
        5, 
        -77
      ], 
      [
        "916.600", 
        4, 
        -80
      ], 
      [
        "916.620", 
        5, 
        -75
      ], 
      [
        "916.640", 
        5, 
        -75
      ], 
      [
        "916.660", 
        5, 
        -76
      ], 
      [
        "916.680", 
        5, 
        -77
      ], 
      [
        "916.700", 
        5, 
        -82
      ]
    ], 
    "setFreq": 916.64, 
    "timestamp": "2016-02-10T12:06:32.000Z", 
    "usedDefault": false
  }
}