{
  "device": "openaps://indy-e1", 
  "pump": {
    "battery": {
      "status": "normal", 
      "voltage": 1.55
    }, 
    "status": {
      "status": "normal", 
      "timestamp": "2016-02-10T08:13:17.000Z", 
      "bolusing": false, 
      "suspended": false
    }, 
    "reservoir": 130.7, 
    "clock": "2016-02-09T23:54:20-08:00"
  }, 
  "openaps": {
    "suggested": {
      "bg": 128, 
      "temp": "absolute", 
      "snoozeBG": 111, 
      "timestamp": "2016-02-10T07:56:05.000Z", 
      "reason": "Eventual BG 111>110 but Delta -3 < Exp. Delta 0; no temp to cancel", 
      "eventualBG": 111, 
      "mealAssist": "Off: Carbs: 0 Boluses: 0 Target: 115 Deviation: -5 BGI: -0.16", 
      "tick": -3
    }, 
    "iob": {
      "netbasalinsulin": 0.5, 
      "timestamp": "2016-02-10T07:56:05.000Z", 
      "basaliob": 0.149, 
      "activity": 0.0004, 
      "bolussnooze": 0, 
      "iob": 0.149
    }, 
    "enacted": {
      "requested": {
        "duration": 0, 
        "rate": 0, 
        "temp": "absolute"
      }, 
      "bg": 131, 
      "temp": "absolute", 
      "snoozeBG": 123, 
      "timestamp": "2016-02-10T07:52:18.000Z", 
      "reason": "Eventual BG 123>110 but Delta -2 < Exp. Delta -0.4; cancel", 
      "rate": 0, 
      "eventualBG": 123, 
      "recieved": true, 
      "duration": 0, 
      "mealAssist": "Off: Carbs: 0 Boluses: 0 Target: 115 Deviation: 4 BGI: -0.2", 
      "tick": -2
    }
  }, 
  "mmtune": {
    "scanDetails": [
      [
        "916.580", 
        2, 
        -90
      ], 
      [
        "916.600", 
        5, 
        -61
      ], 
      [
        "916.620", 
        5, 
        -61
      ], 
      [
        "916.640", 
        5, 
        -61
      ], 
      [
        "916.660", 
        2, 
        -89
      ], 
      [
        "916.820", 
        1, 
        -98
      ]
    ], 
    "setFreq": 916.64, 
    "timestamp": "2016-02-10T08:13:56.000Z", 
    "usedDefault": false
  }
}