{
  "device": "openaps://indy-e1", 
  "pump": {
    "battery": {
      "status": "normal", 
      "voltage": 1.43
    }, 
    "status": {
      "status": "normal", 
      "timestamp": "2016-02-12T14:05:30.000Z", 
      "bolusing": false, 
      "suspended": false
    }, 
    "reservoir": 85.675, 
    "clock": "2016-02-12T06:05:01-08:00"
  }, 
  "openaps": {
    "suggested": {
      "bg": 128, 
      "temp": "absolute", 
      "snoozeBG": 129, 
      "timestamp": "2016-02-12T14:08:05.000Z", 
      "reason": "Eventual BG 129>=120, temp 0.8 >~ req 0.75U/hr", 
      "eventualBG": 129, 
      "mealAssist": "Off: Carbs: 0 Boluses: 0 Target: 115 Deviation: 7 BGI: 0.12", 
      "tick": "+2"
    }, 
    "iob": {
      "netbasalinsulin": -0.05, 
      "timestamp": "2016-02-12T14:08:05.000Z", 
      "basaliob": 0.073, 
      "activity": -0.0003, 
      "bolussnooze": 0, 
      "iob": 0.073
    }, 
    "enacted": {
      "requested": {
        "duration": 30, 
        "rate": 0.8, 
        "temp": "absolute"
      }, 
      "bg": 126, 
      "temp": "absolute", 
      "snoozeBG": 132, 
      "timestamp": "2016-02-12T14:04:13.000Z", 
      "reason": "Eventual BG 132>=120, temp 0.675<0.825U/hr", 
      "rate": 0.8, 
      "eventualBG": 132, 
      "recieved": true, 
      "duration": 30, 
      "mealAssist": "Off: Carbs: 0 Boluses: 0 Target: 115 Deviation: 8 BGI: 0.16", 
      "tick": "+2"
    }
  }, 
  "mmtune": {
    "scanDetails": [
      [
        "916.560", 
        5, 
        -93
      ], 
      [
        "916.580", 
        5, 
        -85
      ], 
      [
        "916.600", 
        5, 
        -83
      ], 
      [
        "916.620", 
        5, 
        -82
      ], 
      [
        "916.640", 
        5, 
        -83
      ], 
      [
        "916.660", 
        5, 
        -82
      ], 
      [
        "916.680", 
        5, 
        -83
      ], 
      [
        "916.700", 
        5, 
        -85
      ], 
      [
        "916.720", 
        5, 
        -94
      ]
    ], 
    "setFreq": 916.66, 
    "timestamp": "2016-02-12T14:05:23.000Z", 
    "usedDefault": false
  }
}