{
  "device": "openaps://indy-e1", 
  "pump": {
    "battery": {
      "status": "normal", 
      "voltage": 1.56
    }, 
    "status": {
      "status": "normal", 
      "timestamp": "2016-02-07T03:23:33.000Z", 
      "bolusing": false, 
      "suspended": false
    }, 
    "reservoir": 110.7, 
    "clock": "2016-02-06T19:23:03-08:00"
  }, 
  "openaps": {
    "suggested": {
      "bg": 102, 
      "temp": "absolute", 
      "snoozeBG": 95, 
      "timestamp": "2016-02-07T03:17:50.000Z", 
      "rate": 0, 
      "reason": "Eventual BG 95<110, setting -0.5U/hr", 
      "eventualBG": 95, 
      "duration": 30, 
      "mealAssist": "Off: Carbs: 3 Boluses: 0.3 Target: 115 Deviation: -21 BGI: -1.24", 
      "tick": -3
    }, 
    "iob": {
      "timestamp": "2016-02-07T03:17:50.000Z", 
      "bolussnooze": 0, 
      "basaliob": -0.208, 
      "iob": -0.177, 
      "activity": 0.0031
    }
  }
}